[{"name": "benchmarks.MetadataSuite.time_load_partition_info_order6", "idx": null, "pretty_name": "benchmarks.MetadataSuite.time_load_partition_info_order6", "last_rev": 678, "last_value": 0.019649721000007503, "last_err": 0.0005128661935420961, "prev_value": null, "change_rev": null}, {"name": "benchmarks.MetadataSuite.time_load_partition_info_order7", "idx": null, "pretty_name": "benchmarks.MetadataSuite.time_load_partition_info_order7", "last_rev": 678, "last_value": 0.0772139489999688, "last_err": 0.000790349174278581, "prev_value": 0.08070452199999067, "change_rev": [638, 651]}, {"name": "benchmarks.MetadataSuite.time_load_partition_join_info", "idx": null, "pretty_name": "benchmarks.MetadataSuite.time_load_partition_join_info", "last_rev": 678, "last_value": 0.07683882299998857, "last_err": 0.0009930044852870024, "prev_value": 0.08041363399999568, "change_rev": [638, 651]}, {"name": "benchmarks.Suite.time_inner_pixel_alignment", "idx": null, "pretty_name": "benchmarks.Suite.time_inner_pixel_alignment", "last_rev": 678, "last_value": 0.012982042499999125, "last_err": 0.00011061988073248585, "prev_value": 0.08740701350001245, "change_rev": [661, 668]}, {"name": "benchmarks.Suite.time_outer_pixel_alignment", "idx": null, "pretty_name": "benchmarks.Suite.time_outer_pixel_alignment", "last_rev": 678, "last_value": 0.3625905625000314, "last_err": 0.00376039176016179, "prev_value": null, "change_rev": null}, {"name": "benchmarks.Suite.time_paths_creation", "idx": null, "pretty_name": "benchmarks.Suite.time_paths_creation", "last_rev": 678, "last_value": 0.08349709700001995, "last_err": 0.002182357187489462, "prev_value": null, "change_rev": null}, {"name": "benchmarks.Suite.time_pixel_tree_creation", "idx": null, "pretty_name": "benchmarks.Suite.time_pixel_tree_creation", "last_rev": 678, "last_value": 0.041029194999993024, "last_err": 0.0006790480806699496, "prev_value": null, "change_rev": null}, {"name": "benchmarks.time_test_alignment_even_sky", "idx": null, "pretty_name": "benchmarks.time_test_alignment_even_sky", "last_rev": 678, "last_value": 0.12371099549999087, "last_err": 0.0020224099771356, "prev_value": 0.17800034000003961, "change_rev": [476, 478]}, {"name": "benchmarks.time_test_cone_filter_multiple_order", "idx": null, "pretty_name": "benchmarks.time_test_cone_filter_multiple_order", "last_rev": 678, "last_value": 0.013586996499995507, "last_err": 0.0012069554544576933, "prev_value": 0.09721716550001247, "change_rev": [638, 651]}]