[{"name": "benchmarks.MetadataSuite.time_load_partition_info_order6", "idx": null, "pretty_name": "benchmarks.MetadataSuite.time_load_partition_info_order6", "last_rev": 602, "last_value": 0.019744725000009566, "last_err": 0.0005006972981072584, "prev_value": null, "change_rev": null}, {"name": "benchmarks.MetadataSuite.time_load_partition_info_order7", "idx": null, "pretty_name": "benchmarks.MetadataSuite.time_load_partition_info_order7", "last_rev": 602, "last_value": 0.08070483350000757, "last_err": 0.0007940125669219994, "prev_value": null, "change_rev": null}, {"name": "benchmarks.MetadataSuite.time_load_partition_join_info", "idx": null, "pretty_name": "benchmarks.MetadataSuite.time_load_partition_join_info", "last_rev": 602, "last_value": 0.08043298100000129, "last_err": 0.0007613085962758381, "prev_value": null, "change_rev": null}, {"name": "benchmarks.Suite.time_pixel_tree_creation", "idx": null, "pretty_name": "benchmarks.Suite.time_pixel_tree_creation", "last_rev": 602, "last_value": 0.6472290339999915, "last_err": 0.005296431568986186, "prev_value": 1.0241116120000129, "change_rev": [476, 478]}, {"name": "benchmarks.time_test_alignment_even_sky", "idx": null, "pretty_name": "benchmarks.time_test_alignment_even_sky", "last_rev": 602, "last_value": 0.12313002950000396, "last_err": 0.002398357624631545, "prev_value": 0.17800034000003961, "change_rev": [476, 478]}, {"name": "benchmarks.time_test_cone_filter_multiple_order", "idx": null, "pretty_name": "benchmarks.time_test_cone_filter_multiple_order", "last_rev": 602, "last_value": 0.0941000090000017, "last_err": 0.0007604581056682977, "prev_value": 0.09781881249999458, "change_rev": [null, 599]}]